tranci/__init__.py
tranci/__main__.py
tranci/py.typed
tranci-1.2.0.dist-info/licenses/LICENSE
tranci-1.2.0.dist-info/METADATA
tranci-1.2.0.dist-info/WHEEL
tranci-1.2.0.dist-info/top_level.txt
tranci-1.2.0.dist-info/RECORD
