Metadata-Version: 2.4
Name: tranci
Version: 1.2.0
Summary: Tranci: a no-dependencies, lightweight, easy-to-use ANSI library
Home-page: https://github.com/Butterroach/tranci
Author: Butterroach
Author-email: butterroach@outlook.com
License: LGPLv3+
Project-URL: Source, https://github.com/Butterroach/tranci
Project-URL: Bug Tracker, https://github.com/Butterroach/tranci/issues
Classifier: Development Status :: 5 - Production/Stable
Classifier: Programming Language :: Python :: 3
Classifier: License :: OSI Approved :: GNU Lesser General Public License v3 or later (LGPLv3+)
Classifier: Intended Audience :: Developers
Classifier: Operating System :: OS Independent
Requires-Python: >=3.9
License-File: LICENSE
Dynamic: author
Dynamic: author-email
Dynamic: classifier
Dynamic: description
Dynamic: description-content-type
Dynamic: home-page
Dynamic: license
Dynamic: license-file
Dynamic: project-url
Dynamic: requires-python
Dynamic: summary
